{
    "sisalto": [
	    {
                "kanavannimi": "NHK",
                "sisalto2": [
					{
				  	"Muoto_JAP":"m3u8",
				  	"Url_JAP":"http://203.162.235.41:16901"
					}
				]
        },
		{
                "kanavannimi": "NHK E",
                "sisalto2": [
					{
				  	"Muoto_JAP":"m3u8",
				  	"Url_JAP":"http://redlabmcdn.s.llnwi.net/jp04/ryowa1hd/playlist.m3u8"
					}
				]
        },
		{
                "kanavannimi": "NHK ENGLISH",
                "sisalto2": [
					{
				  	"Muoto_JAP":"m3u8",
				  	"Url_JAP":"https://nhkworld.webcdn.stream.ne.jp/www11/nhkworld-tv/global/2003458/live.m3u8"
					}
				]
        },
		{
                "kanavannimi": "NHK BSP",
                "sisalto2": [
					{
				  	"Muoto_JAP":"m3u8",
				  	"Url_JAP":"http://redlabmcdn.s.llnwi.net/jp04/bs02hd/playlist.m3u8"
					}
				]
        },
		{
                "kanavannimi": "NHK BS1",
                "sisalto2": [
					{
				  	"Muoto_JAP":"m3u8",
				  	"Url_JAP":"http://redlabmcdn.s.llnwi.net/jp04/bs01hd/playlist.m3u8"
					}
				]
        },
		{
                "kanavannimi": "NHK G",
                "sisalto2": [
					{
				  	"Muoto_JAP":"m3u8",
				  	"Url_JAP":"http://redlabmcdn.s.llnwi.net/jp04/ryowa2hd/playlist.m3u8"
					}
				]
        },
		{
                "kanavannimi": "NHK 华语视界",
                "sisalto2": [
					{
				  	"Muoto_JAP":"m3u8",
				  	"Url_JAP":"https://nhkw-zh-hlscomp.akamaized.net/8thz5iufork8wjip/playlist.m3u8"
					}
				]
        },
		{
                "kanavannimi": "NIPPON TV",
                "sisalto2": [
					{
				  	"Muoto_JAP":"m3u8",
				  	"Url_JAP":"http://redlabmcdn.s.llnwi.net/jp04/ryowa3hd/playlist.m3u8"
					}
				]
        },
		{
                "kanavannimi": "NIPPON TV NEWS 24",
                "sisalto2": [
					{
				  	"Muoto_JAP":"m3u8",
				  	"Url_JAP":"https://www.news24.jp/livestream/index.m3u8"
					},
					{
				  	"Muoto_JAP":"m3u8",
				  	"Url_JAP":"http://redlabmcdn.s.llnwi.net/nv02/ryowa3hd/playlist.m3u8"
					}
				]
        },
		{
                "kanavannimi": "J SPORT 1",
                "sisalto2": [
					{
				  	"Muoto_JAP":"m3u8",
				  	"Url_JAP":"http://redlabmcdn.s.llnwi.net/jp04/bs15hd/playlist.m3u8"
					}
				]
        },
		{
                "kanavannimi": "J SPORT 2",
                "sisalto2": [
					{
				  	"Muoto_JAP":"m3u8",
				  	"Url_JAP":"http://redlabmcdn.s.llnwi.net/jp04/bs11hd/playlist.m3u8"
					}
				]
        },
		{
                "kanavannimi": "J SPORT 3",
                "sisalto2": [
					{
				  	"Muoto_JAP":"m3u8",
				  	"Url_JAP":"http://redlabmcdn.s.llnwi.net/jp04/bs12hd/playlist.m3u8"
					}
				]
        },
		{
                "kanavannimi": "TBS",
                "sisalto2": [
					{
				  	"Muoto_JAP":"m3u8",
				  	"Url_JAP":"http://redlabmcdn.s.llnwi.net/jp04/ryowa5hd/playlist.m3u8"
					}
				]
        },
		{
                "kanavannimi": "TV TOKYO",
                "sisalto2": [
					{
				  	"Muoto_JAP":"m3u8",
				  	"Url_JAP":"http://redlabmcdn.s.llnwi.net/jp04/ryowa6hd/playlist.m3u8"
					}
				]
        },
		{
                "kanavannimi": "TOKYO MX",
                "sisalto2": [
					{
				  	"Muoto_JAP":"m3u8",
				  	"Url_JAP":"http://redlabmcdn.s.llnwi.net/jp04/ryowa8hd/playlist.m3u8"
					}
				]
        },
		{
                "kanavannimi": "STAR CHANNEL 1",
                "sisalto2": [
					{
				  	"Muoto_JAP":"m3u8",
				  	"Url_JAP":"http://redlabmcdn.s.llnwi.net/jp04/bs09hd/playlist.m3u8"
					}
				]
        },
		{
                "kanavannimi": "STAR CHANNEL 2",
                "sisalto2": [
					{
				  	"Muoto_JAP":"m3u8",
				  	"Url_JAP":"http://redlabmcdn.s.llnwi.net/jp04/bs10hd/playlist.m3u8"
					}
				]
        },
		{
                "kanavannimi": "Animax",
                "sisalto2": [
					{
				  	"Muoto_JAP":"m3u8",
				  	"Url_JAP":"http://redlabmcdn.s.llnwi.net/jp04/bs14hd/playlist.m3u8"
					}
				]
        },
		{
                "kanavannimi": "WeatherNews",
                "sisalto2": [
					{
				  	"Muoto_JAP":"m3u8",
				  	"Url_JAP":"http://movie.mcas.jp/mcas/smil:wn1.smil/chunklist_b1800000.m3u8"
					}
				]
        },
		{
                "kanavannimi": "Wowow Cinefil",
                "sisalto2": [
					{
				  	"Muoto_JAP":"m3u8",
				  	"Url_JAP":"http://redlabmcdn.s.llnwi.net/jp04/cs07hd/playlist.m3u8"
					}
				]
        },
	    {
                "kanavannimi": "MUSIC JAPAN",
                "sisalto2": [
					{
				  	"Muoto_JAP":"m3u8",
				  	"Url_JAP":"http://122.155.180.8:5021/live/495"
					}
				]
        },
	    {
                "kanavannimi": "FUJI TV",
                "sisalto2": [
					{
				  	"Muoto_JAP":"m3u8",
				  	"Url_JAP":"http://redlabmcdn.s.llnwi.net/jp04/ryowa7hd/playlist.m3u8"
					}
				]
        },
		{
                "kanavannimi": "TV ASAHI",
                "sisalto2": [
					{
				  	"Muoto_JAP":"m3u8",
				  	"Url_JAP":"http://redlabmcdn.s.llnwi.net/jp04/ryowa4hd/playlist.m3u8"
					}
				]
        },
		{
                "kanavannimi": "KIDS STATION",
                "sisalto2": [
					{
				  	"Muoto_JAP":"m3u8",
				  	"Url_JAP":"http://redlabmcdn.s.llnwi.net/jp04/cs04hd/playlist.m3u8"
					}
				]
        },
		{
                "kanavannimi": "ATX",
                "sisalto2": [
					{
				  	"Muoto_JAP":"m3u8",
				  	"Url_JAP":"https://sub2.neetball.net/live/neet.m3u8"
					}
				]
        },
		{
                "kanavannimi": "DISNEY CHANNEL",
                "sisalto2": [
					{
				  	"Muoto_JAP":"m3u8",
				  	"Url_JAP":"http://redlabmcdn.s.llnwi.net/jp04/bs13hd/playlist.m3u8"
					}
				]
        }
  ]
}